{
    "Ahri": "{\n    \"name\": \"Ahri\",\n    \"stats\": {\n        \"hp\": 570,\n        \"hpperlevel\": 96,\n        \"mp\": 418,\n        \"mpperlevel\": 25,\n        \"movespeed\": 330,\n        \"armor\": 18,\n        \"armorperlevel\": 4.7,\n        \"spellblock\": 30,\n        \"spellblockperlevel\": 1.3,\n        \"attackrange\": 550,\n        \"hpregen\": 2.5,\n        \"hpregenperlevel\": 0.6,\n        \"mpregen\": 8,\n        \"mpregenperlevel\": 0.8,\n        \"crit\": 0,\n        \"critperlevel\": 0,\n        \"attackdamage\": 53,\n        \"attackdamageperlevel\": 3,\n        \"attackspeedperlevel\": 2,\n        \"attackspeed\": 0.668\n    },\n    \"spells\": [\n        {\n            \"spellName\": \"Essence Theft\",\n            \"statuses\": []\n        },\n        {\n            \"spellName\": \"Orb of Deception\",\n            \"statuses\": []\n        },\n        {\n            \"spellName\": \"Fox-Fire\",\n            \"statuses\": []\n        },\n        {\n            \"spellName\": \"Charm\",\n            \"statuses\": [\n                \"Charms\"\n            ]\n        },\n        {\n            \"spellName\": \"Spirit Rush\",\n            \"statuses\": []\n        }\n    ],\n    \"features\": [],\n    \"damageType\": []\n}",
    "Leona": "{\n    \"name\": \"Leona\",\n    \"stats\": {\n        \"hp\": 646,\n        \"hpperlevel\": 101,\n        \"mp\": 302,\n        \"mpperlevel\": 40,\n        \"movespeed\": 335,\n        \"armor\": 47,\n        \"armorperlevel\": 4.8,\n        \"spellblock\": 32,\n        \"spellblockperlevel\": 2.05,\n        \"attackrange\": 125,\n        \"hpregen\": 8.5,\n        \"hpregenperlevel\": 0.85,\n        \"mpregen\": 6,\n        \"mpregenperlevel\": 0.8,\n        \"crit\": 0,\n        \"critperlevel\": 0,\n        \"attackdamage\": 60,\n        \"attackdamageperlevel\": 3,\n        \"attackspeedperlevel\": 2.9,\n        \"attackspeed\": 0.625\n    },\n    \"spells\": [\n        {\n            \"spellName\": \"Sunlight\",\n            \"statuses\": []\n        },\n        {\n            \"spellName\": \"Shield of Daybreak\",\n            \"statuses\": [\n                \"Stuns\"\n            ]\n        },\n        {\n            \"spellName\": \"Eclipse\",\n            \"statuses\": []\n        },\n        {\n            \"spellName\": \"Zenith Blade\",\n            \"statuses\": [\n                \"Rooted\"\n            ]\n        },\n        {\n            \"spellName\": \"Solar Flare\",\n            \"statuses\": [\n                \"Slowing</status> by {{ slowpercent }}% for {{ ccduration }} seconds. Enemies in the center of the flare are <status>Stunned</status> instead of <status>Slowed\"\n            ]\n        }\n    ],\n    \"features\": [],\n    \"damageType\": []\n}",
    "Nautilus": "{\n    \"name\": \"Nautilus\",\n    \"stats\": {\n        \"hp\": 646,\n        \"hpperlevel\": 100,\n        \"mp\": 400,\n        \"mpperlevel\": 47,\n        \"movespeed\": 325,\n        \"armor\": 39,\n        \"armorperlevel\": 4.95,\n        \"spellblock\": 32,\n        \"spellblockperlevel\": 2.05,\n        \"attackrange\": 175,\n        \"hpregen\": 8.5,\n        \"hpregenperlevel\": 0.55,\n        \"mpregen\": 8.63,\n        \"mpregenperlevel\": 0.5,\n        \"crit\": 0,\n        \"critperlevel\": 0,\n        \"attackdamage\": 61,\n        \"attackdamageperlevel\": 3.3,\n        \"attackspeedperlevel\": 1,\n        \"attackspeed\": 0.706\n    },\n    \"spells\": [\n        {\n            \"spellName\": \"Staggering Blow\",\n            \"statuses\": []\n        },\n        {\n            \"spellName\": \"Dredge Line\",\n            \"statuses\": [\n                \"Stunning\"\n            ]\n        },\n        {\n            \"spellName\": \"Titan's Wrath\",\n            \"statuses\": []\n        },\n        {\n            \"spellName\": \"Riptide\",\n            \"statuses\": [\n                \"Slows\"\n            ]\n        },\n        {\n            \"spellName\": \"Depth Charge\",\n            \"statuses\": [\n                \"Knocking</status> them <status>Up</status> and <status>Stunning</status> them for {{ stunduration }} seconds. Other enemies hit by the shockwave are also <status>Knocked Up</status> and <status>Stunned\"\n            ]\n        }\n    ],\n    \"features\": [],\n    \"damageType\": []\n}"
}